VectorX.py
vectorx-1.0.0.dist-info/WHEEL
vectorx-1.0.0.dist-info/METADATA
vectorx-1.0.0.dist-info/RECORD
